{
    "talks": [
        {
          "Title": "How to stay motivated during the CAT preparation? -By Lavanya Borra, 95.73 percentile, IIM Lucknow",
          "URL": "https://dare2compete.com/bites/how-to-stay-motivated-during-the-cat-preparation-by-lavanya-borra-9573-percentile-iim-lucknow",
          "Domain": "Higher Education",
          "Event": "Talks",
          "Image": "https://images.unsplash.com/photo-1531537571171-a707bf2683da?ixlib=rb-1.2.1&ixid=eyJhcHBfaWQiOjEyMDd9&auto=format&fit=crop&w=967&q=80"
        },
        {
          "Title": "The ABC of CAT preparation and mocks -By Mehendi Basu, 98.54 percentile, IIM Kozhikode",
          "URL": "https://dare2compete.com/bites/the-abc-of-cat-preparation-and-mocks-by-mehendi-basu-9854-percentile-iim-kozhikode",
          "Domain": "Higher Education",
          "Event": "Talks",
          "Image": "https://images.unsplash.com/photo-1531537571171-a707bf2683da?ixlib=rb-1.2.1&ixid=eyJhcHBfaWQiOjEyMDd9&auto=format&fit=crop&w=967&q=81"
        },
        {
          "Title": "How to devise a smart strategy for CAT preparation? -By Nitish P Nair, 99.67 percentile, IIM Bangalore",
          "URL": "https://dare2compete.com/bites/how-to-devise-a-smart-strategy-for-cat-preparation-by-nitish-p-nair-9967-percentile-iim-bangalore",
          "Domain": "Higher Education",
          "Event": "Talks",
          "Image": "https://images.unsplash.com/photo-1531537571171-a707bf2683da?ixlib=rb-1.2.1&ixid=eyJhcHBfaWQiOjEyMDd9&auto=format&fit=crop&w=967&q=82"
        },
        {
          "Title": "GRE 2020: Everything you need to know",
          "URL": "https://dare2compete.com/bites/gre-101-everything-you-need-to-know-about-it",
          "Domain": "Higher Education",
          "Event": "Talks",
          "Image": "https://images.unsplash.com/photo-1531537571171-a707bf2683da?ixlib=rb-1.2.1&ixid=eyJhcHBfaWQiOjEyMDd9&auto=format&fit=crop&w=967&q=83"
        },
        {
          "Title": "GRE 2020: Preparation tips for a successful attempt!",
          "URL": "https://dare2compete.com/bites/gre-2020-here-are-the-preparation-tips-for-a-successful-attempt",
          "Domain": "Higher Education",
          "Event": "Talks",
          "Image": "https://images.unsplash.com/photo-1531537571171-a707bf2683da?ixlib=rb-1.2.1&ixid=eyJhcHBfaWQiOjEyMDd9&auto=format&fit=crop&w=967&q=84"
        },
        {
          "Title": "Everything you need to know about GMAT",
          "URL": "https://dare2compete.com/bites/gmat-heres-all-you-need-to-know",
          "Domain": "Higher Education",
          "Event": "Talks",
          "Image": "https://images.unsplash.com/photo-1531537571171-a707bf2683da?ixlib=rb-1.2.1&ixid=eyJhcHBfaWQiOjEyMDd9&auto=format&fit=crop&w=967&q=85"
        },
        {
          "Title": "MBA guide 2020: Best colleges offering Marketing courses in India",
          "URL": "https://dare2compete.com/bites/mba-guide-2020-best-colleges-offering-marketing-courses-in-india",
          "Domain": "Higher Education",
          "Event": "Talks",
          "Image": "https://images.unsplash.com/photo-1531537571171-a707bf2683da?ixlib=rb-1.2.1&ixid=eyJhcHBfaWQiOjEyMDd9&auto=format&fit=crop&w=967&q=86"
        },
        {
          "Title": "IIFT 2020 Notification - Exam dates, pattern, syllabus",
          "URL": "https://dare2compete.com/bites/iift-2020-notification-exam-dates-exam-pattern-syllabus-heres-all-you-need-to-know",
          "Domain": "Higher Education",
          "Event": "Talks",
          "Image": "https://images.unsplash.com/photo-1531537571171-a707bf2683da?ixlib=rb-1.2.1&ixid=eyJhcHBfaWQiOjEyMDd9&auto=format&fit=crop&w=967&q=87"
        },
        {
          "Title": "How I bagged a seat in B-School after scoring 96% in NMAT -By Divyanshi Srivastava from XAHR Bhubaneswar",
          "URL": "https://dare2compete.com/bites/how-i-bagged-a-seat-in-b-school-after-scoring-96-in-nmat-divyanshi-srivastava-xahr-bhubaneswar",
          "Domain": "Higher Education",
          "Event": "Talks",
          "Image": "https://images.unsplash.com/photo-1531537571171-a707bf2683da?ixlib=rb-1.2.1&ixid=eyJhcHBfaWQiOjEyMDd9&auto=format&fit=crop&w=967&q=88"
        },
        {
          "Title": "Appearing for CAT was one of the best decisions of my career -By Akanksha Tandon from UBS Panjab University",
          "URL": "https://dare2compete.com/bites/appearing-for-cat-was-one-of-the-best-decisions-of-my-career-akanksha-tandon-ubs-panjab-university",
          "Domain": "Higher Education",
          "Event": "Talks",
          "Image": "https://images.unsplash.com/photo-1531537571171-a707bf2683da?ixlib=rb-1.2.1&ixid=eyJhcHBfaWQiOjEyMDd9&auto=format&fit=crop&w=967&q=89"
        }
      ]
}